vipaccess/__init__.py
vipaccess/__main__.py
vipaccess/patharg.py
vipaccess/provision.py
vipaccess/version.py
python_vipaccess-0.14.2.dist-info/LICENSE.txt
python_vipaccess-0.14.2.dist-info/METADATA
python_vipaccess-0.14.2.dist-info/WHEEL
python_vipaccess-0.14.2.dist-info/entry_points.txt
python_vipaccess-0.14.2.dist-info/top_level.txt
python_vipaccess-0.14.2.dist-info/RECORD
