Metadata-Version: 2.1
Name: python-vipaccess
Version: 0.14.2
Summary: A free software implementation of Symantec's VIP Access application and protocol
Home-page: https://github.com/dlenski/python-vipaccess
Author: Daniel Lenski
Author-email: dlenski@gmail.com
License: Apache 2.0
Keywords: development
Platform: UNKNOWN
Classifier: Development Status :: 4 - Beta
Classifier: Intended Audience :: Developers
Classifier: Topic :: Software Development :: Libraries :: Python Modules
Classifier: Topic :: Utilities
Classifier: License :: OSI Approved :: Apache Software License
Classifier: Programming Language :: Python :: 2
Classifier: Programming Language :: Python :: 2.7
Classifier: Programming Language :: Python :: 3
Classifier: Programming Language :: Python :: 3.3
Classifier: Programming Language :: Python :: 3.4
Classifier: Programming Language :: Python :: 3.5
Classifier: Programming Language :: Python :: 3.6
Classifier: Programming Language :: Python :: 3.7
Classifier: Programming Language :: Python :: 3.8
Requires-Dist: pycryptodome >=3.6.6
Requires-Dist: oath >=1.4.1
Requires-Dist: requests
